nfl_statistic_book/__init__.py
nfl_statistic_book/nfl_statistic_book.py
nfl_statistic_book/team.py
nfl_statistic_book-1.1.1.dist-info/METADATA
nfl_statistic_book-1.1.1.dist-info/RECORD
nfl_statistic_book-1.1.1.dist-info/WHEEL
nfl_statistic_book-1.1.1.dist-info/entry_points.txt
nfl_statistic_book-1.1.1.dist-info/top_level.txt
