Metadata-Version: 2.1
Name: nfl-statistic-book
Version: 1.1.1
Summary: Python application that retrieves information from MySportsFeed API based on NFL teams
Home-page: https://github.com/kalebswartz7/nfl-statistic-book
Author: Kaleb Swartz
Author-email: kalebswartz7@gmail.com
License: UNKNOWN
Keywords: nfl_statistic_book
Platform: UNKNOWN
Classifier: Development Status :: 2 - Pre-Alpha
Classifier: Intended Audience :: Developers
Classifier: Natural Language :: English
Classifier: Programming Language :: Python :: 3
Classifier: Programming Language :: Python :: 3.4
Classifier: Programming Language :: Python :: 3.5
Classifier: Programming Language :: Python :: 3.6
Requires-Dist: requests
